serena_vbnet/__init__.py
serena_vbnet/cli.py
serena_vbnet/common.py
serena_vbnet/diagnostic.py
serena_vbnet/installer.py
serena_vbnet/vbnet_language_server.py
serena_vbnet-1.0.29.dist-info/licenses/LICENSE
serena_vbnet-1.0.29.dist-info/METADATA
serena_vbnet-1.0.29.dist-info/WHEEL
serena_vbnet-1.0.29.dist-info/entry_points.txt
serena_vbnet-1.0.29.dist-info/top_level.txt
serena_vbnet-1.0.29.dist-info/RECORD
