Metadata-Version: 2.4
Name: serena-vbnet
Version: 1.0.29
Summary: Visual Basic .NET language support for Serena MCP Server
Author: LaunchCG
License: MIT
Project-URL: Homepage, https://github.com/LaunchCG/serena-vbnet
Project-URL: Repository, https://github.com/LaunchCG/serena-vbnet
Project-URL: Issues, https://github.com/LaunchCG/serena-vbnet/issues
Project-URL: Documentation, https://github.com/LaunchCG/serena-vbnet#readme
Keywords: vb.net,visual-basic,language-server,serena,mcp,ai
Classifier: Development Status :: 4 - Beta
Classifier: Intended Audience :: Developers
Classifier: License :: OSI Approved :: MIT License
Classifier: Programming Language :: Python :: 3
Classifier: Programming Language :: Python :: 3.11
Classifier: Programming Language :: Python :: 3.12
Classifier: Topic :: Software Development :: Code Generators
Classifier: Topic :: Software Development :: Compilers
Requires-Python: >=3.11
License-File: LICENSE
Requires-Dist: click>=8.0.0
Requires-Dist: requests>=2.28.0
Provides-Extra: dev
Requires-Dist: pytest>=7.0.0; extra == "dev"
Requires-Dist: black>=22.0.0; extra == "dev"
Requires-Dist: mypy>=0.990; extra == "dev"
Requires-Dist: build>=0.10.0; extra == "dev"
Requires-Dist: twine>=4.0.0; extra == "dev"
Dynamic: license-file
